disagreement/__init__.py
disagreement/audio.py
disagreement/cache.py
disagreement/caching.py
disagreement/client.py
disagreement/color.py
disagreement/components.py
disagreement/enums.py
disagreement/error_handler.py
disagreement/errors.py
disagreement/event_dispatcher.py
disagreement/gateway.py
disagreement/http.py
disagreement/hybrid_context.py
disagreement/i18n.py
disagreement/interactions.py
disagreement/logging_config.py
disagreement/models.py
disagreement/oauth.py
disagreement/permissions.py
disagreement/py.typed
disagreement/rate_limiter.py
disagreement/shard_manager.py
disagreement/typing.py
disagreement/utils.py
disagreement/voice_client.py
disagreement/ext/__init__.py
disagreement/ext/loader.py
disagreement/ext/tasks.py
disagreement/ext/app_commands/__init__.py
disagreement/ext/app_commands/commands.py
disagreement/ext/app_commands/context.py
disagreement/ext/app_commands/converters.py
disagreement/ext/app_commands/decorators.py
disagreement/ext/app_commands/handler.py
disagreement/ext/app_commands/hybrid.py
disagreement/ext/commands/__init__.py
disagreement/ext/commands/cog.py
disagreement/ext/commands/converters.py
disagreement/ext/commands/core.py
disagreement/ext/commands/decorators.py
disagreement/ext/commands/errors.py
disagreement/ext/commands/help.py
disagreement/ext/commands/view.py
disagreement/ui/__init__.py
disagreement/ui/button.py
disagreement/ui/item.py
disagreement/ui/modal.py
disagreement/ui/select.py
disagreement/ui/view.py
disagreement-0.8.1.dist-info/licenses/LICENSE
disagreement-0.8.1.dist-info/METADATA
disagreement-0.8.1.dist-info/WHEEL
disagreement-0.8.1.dist-info/top_level.txt
disagreement-0.8.1.dist-info/RECORD
