Metadata-Version: 2.4
Name: disagreement
Version: 0.8.1
Summary: A Python library for the Discord API.
Author-email: Slipstream <me@slipstreamm.dev>
License: BSD 3-Clause
Project-URL: Homepage, https://github.com/Slipstreamm/disagreement
Project-URL: Issues, https://github.com/Slipstreamm/disagreement/issues
Project-URL: Documentation, https://disagreement.xyz/
Keywords: discord,api,bot,async,aiohttp
Classifier: Development Status :: 4 - Beta
Classifier: Intended Audience :: Developers
Classifier: License :: OSI Approved :: BSD License
Classifier: Operating System :: OS Independent
Classifier: Programming Language :: Python :: 3
Classifier: Programming Language :: Python :: 3.10
Classifier: Programming Language :: Python :: 3.11
Classifier: Programming Language :: Python :: 3.12
Classifier: Programming Language :: Python :: 3.13
Classifier: Topic :: Software Development :: Libraries
Classifier: Topic :: Software Development :: Libraries :: Python Modules
Classifier: Topic :: Internet
Requires-Python: >=3.10
License-File: LICENSE
Requires-Dist: aiohttp<4.0.0,>=3.9.0
Requires-Dist: PyNaCl<2.0.0,>=1.5.0
Provides-Extra: test
Requires-Dist: pytest>=8.0.0; extra == "test"
Requires-Dist: pytest-asyncio>=1.0.0; extra == "test"
Requires-Dist: hypothesis>=6.132.0; extra == "test"
Provides-Extra: dev
Requires-Dist: python-dotenv>=1.0.0; extra == "dev"
Dynamic: license-file
